{
  "@context": "https://doi.org/10.5063/schema/codemeta-2.0",
  "@type": "SoftwareSourceCode",
  "identifier": "moveability",
  "description": "Moveability statistics for any specified city.",
  "name": "moveability: Moveability statistics for any specified city",
  "codeRepository": "https://github.com/moveability/moveability",
  "issueTracker": "https://github.com/moveability/moveability/issues",
  "license": "https://spdx.org/licenses/GPL-3.0",
  "version": "0.0.0.9",
  "programmingLanguage": {
    "@type": "ComputerLanguage",
    "name": "R",
    "url": "https://r-project.org"
  },
  "runtimePlatform": "R version 4.1.2 (2021-11-01)",
  "author": [
    {
      "@type": "Person",
      "givenName": "Mark",
      "familyName": "Padgham",
      "email": "mark.padgham@email.com"
    }
  ],
  "copyrightHolder": [
    {
      "@type": "Person",
      "givenName": "Angus",
      "familyName": "Johnson"
    }
  ],
  "maintainer": [
    {
      "@type": "Person",
      "givenName": "Mark",
      "familyName": "Padgham",
      "email": "mark.padgham@email.com"
    }
  ],
  "softwareSuggestions": [
    {
      "@type": "SoftwareApplication",
      "identifier": "geodist",
      "name": "geodist",
      "provider": {
        "@id": "https://cran.r-project.org",
        "@type": "Organization",
        "name": "Comprehensive R Archive Network (CRAN)",
        "url": "https://cran.r-project.org"
      },
      "sameAs": "https://CRAN.R-project.org/package=geodist"
    },
    {
      "@type": "SoftwareApplication",
      "identifier": "knitr",
      "name": "knitr",
      "provider": {
        "@id": "https://cran.r-project.org",
        "@type": "Organization",
        "name": "Comprehensive R Archive Network (CRAN)",
        "url": "https://cran.r-project.org"
      },
      "sameAs": "https://CRAN.R-project.org/package=knitr"
    },
    {
      "@type": "SoftwareApplication",
      "identifier": "testthat",
      "name": "testthat",
      "provider": {
        "@id": "https://cran.r-project.org",
        "@type": "Organization",
        "name": "Comprehensive R Archive Network (CRAN)",
        "url": "https://cran.r-project.org"
      },
      "sameAs": "https://CRAN.R-project.org/package=testthat"
    }
  ],
  "softwareRequirements": {
    "1": {
      "@type": "SoftwareApplication",
      "identifier": "R",
      "name": "R",
      "version": ">= 2.10"
    },
    "2": {
      "@type": "SoftwareApplication",
      "identifier": "dodgr",
      "name": "dodgr",
      "provider": {
        "@id": "https://cran.r-project.org",
        "@type": "Organization",
        "name": "Comprehensive R Archive Network (CRAN)",
        "url": "https://cran.r-project.org"
      },
      "sameAs": "https://github.com/atfutures/dodgr"
    },
    "3": {
      "@type": "SoftwareApplication",
      "identifier": "dplyr",
      "name": "dplyr",
      "provider": {
        "@id": "https://cran.r-project.org",
        "@type": "Organization",
        "name": "Comprehensive R Archive Network (CRAN)",
        "url": "https://cran.r-project.org"
      },
      "sameAs": "https://CRAN.R-project.org/package=dplyr"
    },
    "4": {
      "@type": "SoftwareApplication",
      "identifier": "magrittr",
      "name": "magrittr",
      "provider": {
        "@id": "https://cran.r-project.org",
        "@type": "Organization",
        "name": "Comprehensive R Archive Network (CRAN)",
        "url": "https://cran.r-project.org"
      },
      "sameAs": "https://CRAN.R-project.org/package=magrittr"
    },
    "5": {
      "@type": "SoftwareApplication",
      "identifier": "methods",
      "name": "methods"
    },
    "6": {
      "@type": "SoftwareApplication",
      "identifier": "osmdata",
      "name": "osmdata",
      "provider": {
        "@id": "https://cran.r-project.org",
        "@type": "Organization",
        "name": "Comprehensive R Archive Network (CRAN)",
        "url": "https://cran.r-project.org"
      },
      "sameAs": "https://CRAN.R-project.org/package=osmdata"
    },
    "7": {
      "@type": "SoftwareApplication",
      "identifier": "pbapply",
      "name": "pbapply",
      "provider": {
        "@id": "https://cran.r-project.org",
        "@type": "Organization",
        "name": "Comprehensive R Archive Network (CRAN)",
        "url": "https://cran.r-project.org"
      },
      "sameAs": "https://CRAN.R-project.org/package=pbapply"
    },
    "8": {
      "@type": "SoftwareApplication",
      "identifier": "Rcpp",
      "name": "Rcpp",
      "version": ">= 0.12.6",
      "provider": {
        "@id": "https://cran.r-project.org",
        "@type": "Organization",
        "name": "Comprehensive R Archive Network (CRAN)",
        "url": "https://cran.r-project.org"
      },
      "sameAs": "https://CRAN.R-project.org/package=Rcpp"
    },
    "9": {
      "@type": "SoftwareApplication",
      "identifier": "RcppParallel",
      "name": "RcppParallel",
      "provider": {
        "@id": "https://cran.r-project.org",
        "@type": "Organization",
        "name": "Comprehensive R Archive Network (CRAN)",
        "url": "https://cran.r-project.org"
      },
      "sameAs": "https://CRAN.R-project.org/package=RcppParallel"
    },
    "10": {
      "@type": "SoftwareApplication",
      "identifier": "sf",
      "name": "sf",
      "provider": {
        "@id": "https://cran.r-project.org",
        "@type": "Organization",
        "name": "Comprehensive R Archive Network (CRAN)",
        "url": "https://cran.r-project.org"
      },
      "sameAs": "https://CRAN.R-project.org/package=sf"
    },
    "SystemRequirements": "C++11, GNU make"
  },
  "fileSize": "22199.815KB",
  "readme": "https://github.com/moveability/moveability/blob/master/README.md",
  "developmentStatus": "http://www.repostatus.org/#concept"
}
